{"cameraMode":{"drawMode":0,"name":"Shaded","section":"Shading Mode"},"sceneLighting":true,"audioPlay":false,"sceneViewState":{"showFog":true,"showMaterialUpdate":false,"showSkybox":true,"showFlares":true,"showImageEffects":true,"showParticleSystems":true},"in2DMode":false,"pivot":{"x":3.48612904548645,"y":0.27007588744163515,"z":-1.4298672676086426},"rotation":{"x":0.20416386425495149,"y":-0.318310409784317,"z":0.0704072117805481,"w":0.9230597019195557},"size":2.407017707824707,"orthographic":false}